Workbook

Sheet Dashboard
B2: DESCENTRALIZADOS — OPERATIVA FUTUROS PIONEX
B4: % Medio de Ganancia por Operación | D4: Balance Total ($) | F4: Media de Ganancia Diaria ($)
B5: =AVERAGE(Operaciones!K2:K446) -> 0.020261988 | D5: =SUM(Operaciones!J2:J446) -> 3482.58 | F5: =AVERAGE('Resumen Diario'!C2:C117) -> 30.022241
B7: Total operaciones | D7: Días operados | F7: Win rate
B8: =COUNTA(Operaciones!B2:B446) -> 445 | D8: =COUNTA('Resumen Diario'!A2:A117) -> 116 | F8: =COUNTIF(Operaciones!J2:J446,">0")/COUNTA(Operaciones!B2:B446) -> 0.77752809

Sheet Operaciones
A1: Fecha Cierre | B1: Símbolo | C1: Lado | D1: Tipo | E1: Promedios | F1: Capital Desplegado ($) | G1: PnL Bruto ($) | H1: Comisiones ($) | I1: Funding ($) | J1: PnL Neto ($) | K1: Rentabilidad % | L1: Resultado
A2: 46074.696 | B2: BIO | C2: Short | D2: Manual | E2: 0 | F2: 999.98 | G2: 100.91 | H2: -0.95 | I2: -13.31 | J2: =G2+H2+I2 -> 86.65 | K2: =IF(F2>0,J2/F2,"") -> 0.086651733 | L2: TP directo
A3: 46075.293 | B3: YGG | C3: Short | D3: Manual | E3: 0 | F3: 1094.5 | G3: 104.56 | H3: -1.04 | I3: -11.57 | J3: =G3+H3+I3 -> 91.95 | K3: =IF(F3>0,J3/F3,"") -> 0.084010964 | L3: TP directo
A4: 46076.643 | B4: AZTEC | C4: Short | D4: Manual | E4: 0 | F4: 781.09 | G4: 68.56 | H4: -0.75 | I4: -129.01 | J4: =G4+H4+I4 -> -61.2 | K4: =IF(F4>0,J4/F4,"") -> -0.078352046 | L4: Cerrada en pérdida
A5: 46076.643 | B5: AGLD | C5: Short | D5: Manual | E5: 0 | F5: 1020.87 | G5: 49.93 | H5: -1 | I5: -16.65 | J5: =G5+H5+I5 -> 32.28 | K5: =IF(F5>0,J5/F5,"") -> 0.031620089 | L5: TP directo
A6: 46077.054 | B6: FLOCK | C6: Short | D6: Manual | E6: 0 | F6: 999.96 | G6: 101.33 | H6: -0.74 | I6: -5.4 | J6: =G6+H6+I6 -> 95.19 | K6: =IF(F6>0,J6/F6,"") -> 0.095193808 | L6: TP directo
A7: 46079.318 | B7: AKE | C7: Short | D7: Manual | E7: 1 | F7: 1484.89 | G7: 30.81 | H7: -1.47 | I7: 10.69 | J7: =G7+H7+I7 -> 40.03 | K7: =IF(F7>0,J7/F7,"") -> 0.026958226 | L7: TP tras 1 promedio(s)
A8: 46079.674 | B8: GRIFFAIN | C8: Short | D8: Manual | E8: 0 | F8: 249.5 | G8: 1.07 | H8: -0.25 | I8: 0.04 | J8: =G8+H8+I8 -> 0.86 | K8: =IF(F8>0,J8/F8,"") -> 0.0034468938 | L8: TP directo
A9: 46079.752 | B9: OPENEDEN | C9: Short | D9: Manual | E9: 0 | F9: 1999.97 | G9: 144.14 | H9: -1.93 | I9: 0.09 | J9: =G9+H9+I9 -> 142.3 | K9: =IF(F9>0,J9/F9,"") -> 0.071151067 | L9: TP directo
A10: 46079.752 | B10: AXL | C10: Short | D10: Manual | E10: 0 | F10: 999.97 | G10: 85.24 | H10: -0.96 | I10: -18.42 | J10: =G10+H10+I10 -> 65.86 | K10: =IF(F10>0,J10/F10,"") -> 0.065861976 | L10: TP directo
A11: 46080.298 | B11: B | C11: Short | D11: Manual | E11: 0 | F11: 999.91 | G11: 3.05 | H11: -1 | I11: 0 | J11: =G11+H11+I11 -> 2.05 | K11: =IF(F11>0,J11/F11,"") -> 0.0020501845 | L11: TP directo
A12: 46080.307 | B12: LUNC | C12: Short | D12: Manual | E12: 0 | F12: 2500 | G12: 154.07 | H12: -2.42 | I12: 0 | J12: =G12+H12+I12 -> 151.65 | K12: =IF(F12>0,J12/F12,"") -> 0.06066 | L12: TP directo
A13: 46080.408 | B13: FOLKS | C13: Short | D13: Manual | E13: 0 | F13: 1499.94 | G13: 80.7 | H13: -1.46 | I13: 0 | J13: =G13+H13+I13 -> 79.24 | K13: =IF(F13>0,J13/F13,"") -> 0.05282878 | L13: TP directo
... A446: 46212.531 | B446: EVAA | C446: Short | D446: Manual | E446: 0 | F446: 1000 | G446: 200.32 | H446: 0 | I446: 0 | J446: =G446+H446+I446 -> 200.32 | K446: =IF(F446>0,J446/F446,"") -> 0.20032 | L446: TP directo

Sheet Resumen Diario
A1: Fecha | B1: Nº Operaciones | C1: PnL Neto Día ($) | D1: Rentabilidad Media Día | E1: Balance Acumulado ($)
A2: 46074 | B2: =COUNTIFS(Operaciones!$A$2:$A$446,">="&A2,Operaciones!$A$2:$A$446,"<"&A2+1) -> 1 | C2: =SUMIFS(Operaciones!$J$2:$J$446,Operaciones!$A$2:$A$446,">="&A2,Operaciones!$A$2:$A$446,"<"&A2+1) -> 86.65 | D2: =IFERROR(AVERAGEIFS(Operaciones!$K$2:$K$446,Operaciones!$A$2:$A$446,">="&A2,Operaciones!$A$2:$A$446,"<"&A2+1),"") -> 0.086651733 | E2: =C2 -> 86.65
A3: 46075 | B3: =COUNTIFS(Operaciones!$A$2:$A$446,">="&A3,Operaciones!$A$2:$A$446,"<"&A3+1) -> 1 | C3: =SUMIFS(Operaciones!$J$2:$J$446,Operaciones!$A$2:$A$446,">="&A3,Operaciones!$A$2:$A$446,"<"&A3+1) -> 91.95 | D3: =IFERROR(AVERAGEIFS(Operaciones!$K$2:$K$446,Operaciones!$A$2:$A$446,">="&A3,Operaciones!$A$2:$A$446,"<"&A3+1),"") -> 0.084010964 | E3: =E2+C3 -> 178.6
A4: 46076 | B4: =COUNTIFS(Operaciones!$A$2:$A$446,">="&A4,Operaciones!$A$2:$A$446,"<"&A4+1) -> 2 | C4: =SUMIFS(Operaciones!$J$2:$J$446,Operaciones!$A$2:$A$446,">="&A4,Operaciones!$A$2:$A$446,"<"&A4+1) -> -28.92 | D4: =IFERROR(AVERAGEIFS(Operaciones!$K$2:$K$446,Operaciones!$A$2:$A$446,">="&A4,Operaciones!$A$2:$A$446,"<"&A4+1),"") -> -0.023365979 | E4: =E3+C4 -> 149.68
A5: 46077 | B5: =COUNTIFS(Operaciones!$A$2:$A$446,">="&A5,Operaciones!$A$2:$A$446,"<"&A5+1) -> 1 | C5: =SUMIFS(Operaciones!$J$2:$J$446,Operaciones!$A$2:$A$446,">="&A5,Operaciones!$A$2:$A$446,"<"&A5+1) -> 95.19 | D5: =IFERROR(AVERAGEIFS(Operaciones!$K$2:$K$446,Operaciones!$A$2:$A$446,">="&A5,Operaciones!$A$2:$A$446,"<"&A5+1),"") -> 0.095193808 | E5: =E4+C5 -> 244.87
A6: 46079 | B6: =COUNTIFS(Operaciones!$A$2:$A$446,">="&A6,Operaciones!$A$2:$A$446,"<"&A6+1) -> 4 | C6: =SUMIFS(Operaciones!$J$2:$J$446,Operaciones!$A$2:$A$446,">="&A6,Operaciones!$A$2:$A$446,"<"&A6+1) -> 249.05 | D6: =IFERROR(AVERAGEIFS(Operaciones!$K$2:$K$446,Operaciones!$A$2:$A$446,">="&A6,Operaciones!$A$2:$A$446,"<"&A6+1),"") -> 0.041854541 | E6: =E5+C6 -> 493.92
A7: 46080 | B7: =COUNTIFS(Operaciones!$A$2:$A$446,">="&A7,Operaciones!$A$2:$A$446,"<"&A7+1) -> 6 | C7: =SUMIFS(Operaciones!$J$2:$J$446,Operaciones!$A$2:$A$446,">="&A7,Operaciones!$A$2:$A$446,"<"&A7+1) -> 320.57 | D7: =IFERROR(AVERAGEIFS(Operaciones!$K$2:$K$446,Operaciones!$A$2:$A$446,">="&A7,Operaciones!$A$2:$A$446,"<"&A7+1),"") -> 0.033861494 | E7: =E6+C7 -> 814.49
A8: 46081 | B8: =COUNTIFS(Operaciones!$A$2:$A$446,">="&A8,Operaciones!$A$2:$A$446,"<"&A8+1) -> 3 | C8: =SUMIFS(Operaciones!$J$2:$J$446,Operaciones!$A$2:$A$446,">="&A8,Operaciones!$A$2:$A$446,"<"&A8+1) -> 73.46 | D8: =IFERROR(AVERAGEIFS(Operaciones!$K$2:$K$446,Operaciones!$A$2:$A$446,">="&A8,Operaciones!$A$2:$A$446,"<"&A8+1),"") -> 0.032958847 | E8: =E7+C8 -> 887.95
A9: 46082 | B9: =COUNTIFS(Operaciones!$A$2:$A$446,">="&A9,Operaciones!$A$2:$A$446,"<"&A9+1) -> 3 | C9: =SUMIFS(Operaciones!$J$2:$J$446,Operaciones!$A$2:$A$446,">="&A9,Operaciones!$A$2:$A$446,"<"&A9+1) -> 370.72 | D9: =IFERROR(AVERAGEIFS(Operaciones!$K$2:$K$446,Operaciones!$A$2:$A$446,">="&A9,Operaciones!$A$2:$A$446,"<"&A9+1),"") -> 0.059375957 | E9: =E8+C9 -> 1258.67
A10: 46083 | B10: =COUNTIFS(Operaciones!$A$2:$A$446,">="&A10,Operaciones!$A$2:$A$446,"<"&A10+1) -> 8 | C10: =SUMIFS(Operaciones!$J$2:$J$446,Operaciones!$A$2:$A$446,">="&A10,Operaciones!$A$2:$A$446,"<"&A10+1) -> 618.23 | D10: =IFERROR(AVERAGEIFS(Operaciones!$K$2:$K$446,Operaciones!$A$2:$A$446,">="&A10,Operaciones!$A$2:$A$446,"<"&A10+1),"") -> 0.039795065 | E10: =E9+C10 -> 1876.9
A11: 46084 | B11: =COUNTIFS(Operaciones!$A$2:$A$446,">="&A11,Operaciones!$A$2:$A$446,"<"&A11+1) -> 8 | C11: =SUMIFS(Operaciones!$J$2:$J$446,Operaciones!$A$2:$A$446,">="&A11,Operaciones!$A$2:$A$446,"<"&A11+1) -> 446.96 | D11: =IFERROR(AVERAGEIFS(Operaciones!$K$2:$K$446,Operaciones!$A$2:$A$446,">="&A11,Operaciones!$A$2:$A$446,"<"&A11+1),"") -> 0.027935087 | E11: =E10+C11 -> 2323.86
A12: 46085 | B12: =COUNTIFS(Operaciones!$A$2:$A$446,">="&A12,Operaciones!$A$2:$A$446,"<"&A12+1) -> 2 | C12: =SUMIFS(Operaciones!$J$2:$J$446,Operaciones!$A$2:$A$446,">="&A12,Operaciones!$A$2:$A$446,"<"&A12+1) -> 24.43 | D12: =IFERROR(AVERAGEIFS(Operaciones!$K$2:$K$446,Operaciones!$A$2:$A$446,">="&A12,Operaciones!$A$2:$A$446,"<"&A12+1),"") -> 0.00088151263 | E12: =E11+C12 -> 2348.29
A13: 46086 | B13: =COUNTIFS(Operaciones!$A$2:$A$446,">="&A13,Operaciones!$A$2:$A$446,"<"&A13+1) -> 10 | C13: =SUMIFS(Operaciones!$J$2:$J$446,Operaciones!$A$2:$A$446,">="&A13,Operaciones!$A$2:$A$446,"<"&A13+1) -> 631.16 | D13: =IFERROR(AVERAGEIFS(Operaciones!$K$2:$K$446,Operaciones!$A$2:$A$446,">="&A13,Operaciones!$A$2:$A$446,"<"&A13+1),"") -> 0.029940342 | E13: =E12+C13 -> 2979.45
A14: 46087 | B14: =COUNTIFS(Operaciones!$A$2:$A$446,">="&A14,Operaciones!$A$2:$A$446,"<"&A14+1) -> 5 | C14: =SUMIFS(Operaciones!$J$2:$J$446,Operaciones!$A$2:$A$446,">="&A14,Operaciones!$A$2:$A$446,"<"&A14+1) -> 349.89 | D14: =IFERROR(AVERAGEIFS(Operaciones!$K$2:$K$446,Operaciones!$A$2:$A$446,">="&A14,Operaciones!$A$2:$A$446,"<"&A14+1),"") -> 0.026682941 | E14: =E13+C14 -> 3329.34
... A117: 46212 | B117: =COUNTIFS(Operaciones!$A$2:$A$446,">="&A117,Operaciones!$A$2:$A$446,"<"&A117+1) -> 2 | C117: =SUMIFS(Operaciones!$J$2:$J$446,Operaciones!$A$2:$A$446,">="&A117,Operaciones!$A$2:$A$446,"<"&A117+1) -> 404.82 | D117: =IFERROR(AVERAGEIFS(Operaciones!$K$2:$K$446,Operaciones!$A$2:$A$446,">="&A117,Operaciones!$A$2:$A$446,"<"&A117+1),"") -> 0.20241 | E117: =E116+C117 -> 3482.58
